clapy/__init__.py
clapy/common.py
clapy/dependency_injection.py
clapy/engine.py
clapy/exceptions.py
clapy/outputs.py
clapy/pipeline.py
clapy/services.py
clapy/utils.py
clapy-2.2.6.dist-info/LICENCE
clapy-2.2.6.dist-info/METADATA
clapy-2.2.6.dist-info/WHEEL
clapy-2.2.6.dist-info/top_level.txt
clapy-2.2.6.dist-info/RECORD
