Metadata-Version: 2.1
Name: clapy
Version: 2.2.6
Summary: Automated invocation of clean architecture use cases in Python.
Author-email: Ben Talese <ben.talese@gmail.com>
License: MIT License
Project-URL: homepage, https://github.com/BenTalese/clapy
Keywords: clean,architecture,clapy,use,case,use-case,design,patterns,python3,asyncio,dependency,injection,onion
Classifier: License :: OSI Approved :: MIT License
Classifier: Intended Audience :: Developers
Classifier: Framework :: AsyncIO
Classifier: Development Status :: 5 - Production/Stable
Classifier: Topic :: Software Development :: Libraries :: Python Modules
Classifier: Programming Language :: Python
Classifier: Programming Language :: Python :: 3
Classifier: Programming Language :: Python :: 3.7
Classifier: Programming Language :: Python :: 3.8
Classifier: Programming Language :: Python :: 3.9
Classifier: Programming Language :: Python :: 3.10
Classifier: Programming Language :: Python :: 3.11
Requires-Python: >=3.7
License-File: LICENCE
Provides-Extra: dependency_injector
Requires-Dist: dependency-injector >=4.41.0 ; extra == 'dependency_injector'
